format_logger/__init__.py
format_logger/logger.py
format_logger-0.0.5.dist-info/LICENCE
format_logger-0.0.5.dist-info/METADATA
format_logger-0.0.5.dist-info/WHEEL
format_logger-0.0.5.dist-info/entry_points.txt
format_logger-0.0.5.dist-info/top_level.txt
format_logger-0.0.5.dist-info/RECORD
