Metadata-Version: 2.1
Name: format_logger
Version: 0.0.5
Summary: Description.
Home-page: https://github.com/echang1802/format-logger
Author: Eloy Chang
Author-email: echang.epsilondl@gmail.com
Classifier: Programming Language :: Python :: 3
Classifier: License :: OSI Approved :: MIT License
Classifier: Operating System :: OS Independent
Requires-Python: >=3.6
License-File: LICENCE
